psyaitools/.DS_Store
psyaitools/__init__.py
psyaitools/func/IO/__init__.py
psyaitools/func/IO/base64_wav.py
psyaitools/func/IO/base64_xfccs.py
psyaitools/func/IO/readFiles.py
psyaitools/func/__init__.py
psyaitools/func/ext/__init__.py
psyaitools/func/ext/shInst.py
psyaitools/func/representation/__init__.py
psyaitools/func/representation/factDecomMachine.py
psyaitools/func/representation/loud.py
psyaitools/func/representation/xfccs.py
psyaitools/res/BSD_3_LICENSE_spafe
psyaitools/res/res.py
psyaitools-0.1.6.dist-info/LICENSE
psyaitools-0.1.6.dist-info/METADATA
psyaitools-0.1.6.dist-info/WHEEL
psyaitools-0.1.6.dist-info/RECORD
