Metadata-Version: 2.1
Name: psyaitools
Version: 0.1.6
Summary: Loudness added.
Author: moomoofarm1
Author-email: 46774289+moomoofarm1@users.noreply.github.com
Requires-Python: >=3.9,<4.0
Classifier: Programming Language :: Python :: 3
Classifier: Programming Language :: Python :: 3.9
Classifier: Programming Language :: Python :: 3.10
Classifier: Programming Language :: Python :: 3.11
Requires-Dist: audioread (>=3.0,<4.0)
Requires-Dist: numpy (>=1.24,<2.0)
Requires-Dist: pandas (>=2.2,<3.0)
Requires-Dist: pyloudnorm (>=0.1,<0.2)
Requires-Dist: pyspark (>=3.5,<4.0)
Requires-Dist: scipy (>=1.13,<2.0)
Requires-Dist: spafe (>=0.3,<0.4)
